jokes_daily/__init__.py
jokes_daily/cli.py
jokes_daily/core.py
jokes_daily-0.1.3.dist-info/entry_points.txt
jokes_daily-0.1.3.dist-info/LICENSE
jokes_daily-0.1.3.dist-info/WHEEL
jokes_daily-0.1.3.dist-info/METADATA
jokes_daily-0.1.3.dist-info/RECORD
