Metadata-Version: 2.1
Name: jokes_daily
Version: 0.1.3
Summary: jokes_daily is a python cli app to generate jokes from your terminal
Author-email: Nikhil Akki <nikhil.akki@outlook.com>
Classifier: License :: OSI Approved :: MIT License
Project-URL: Home, https://github.com/nikhilakki/nikhilakki.in-blog-code-examples/tree/main/jokes_daily
